N_HANS
