Metadata-Version: 1.1
Name: N-HANS
Version: 2020.6.22
Summary: Neuro-Holistic Audio-eNhancement System
Home-page: https://github.com/N-HANS/N-HANS
Author: Shuo Liu, Gil Keren, Bjoern Schuller
Author-email: shuo.liu@informatik.uni-augsburg.de
License: License :: OSI Approved :: GNU General Public License v3 (GPLv3)
Platform: UNKNOWN
Classifier: Development Status :: 4 - Beta
Classifier: Topic :: Multimedia :: Sound/Audio
Classifier: Topic :: Multimedia :: Sound/Audio :: Speech
Classifier: License :: OSI Approved :: GNU General Public License v3 (GPLv3)
Classifier: Programming Language :: Python :: 3
